wap/__init__.py
wap/__main__.py
wap/config.py
wap/console.py
wap/core.py
wap/curseforge.py
wap/exception.py
wap/fileops.py
wap/prompt.py
wap/toc.py
wap/wow.py
wap/commands/__init__.py
wap/commands/base.py
wap/commands/build.py
wap/commands/new_config.py
wap/commands/new_project.py
wap/commands/publish.py
wap/commands/util.py
wap/commands/validate.py
wap/schema/wap.schema.json
wap/versions/latest.json
wow_addon_packager-0.13.0.dist-info/METADATA
wow_addon_packager-0.13.0.dist-info/WHEEL
wow_addon_packager-0.13.0.dist-info/entry_points.txt
wow_addon_packager-0.13.0.dist-info/licenses/LICENSE.md
wow_addon_packager-0.13.0.dist-info/RECORD
