Metadata-Version: 2.4
Name: wow-addon-packager
Version: 0.13.0
Summary: A developer-friendly World of Warcraft addon packager
Author-email: Tim Martin <tim@timmart.in>
License-Expression: MIT
License-File: LICENSE.md
Keywords: Addons,WoW,World of Warcraft
Classifier: Development Status :: 4 - Beta
Classifier: Environment :: Console
Classifier: Intended Audience :: Developers
Classifier: License :: OSI Approved :: MIT License
Classifier: Natural Language :: English
Classifier: Operating System :: OS Independent
Classifier: Programming Language :: Python
Classifier: Programming Language :: Python :: 3
Classifier: Programming Language :: Python :: 3.13
Classifier: Topic :: Software Development :: Build Tools
Requires-Python: >=3.13
Requires-Dist: arrow>=1.3.0
Requires-Dist: attrs>=24.3.0
Requires-Dist: click>=8.1.8
Requires-Dist: httpx>=0.28.1
Requires-Dist: jsonschema>=4.23.0
Requires-Dist: respx>=0.22.0
Requires-Dist: rich>=13.9.4
Requires-Dist: watchfiles>=1.0.4
